kadmin/__init__.py
kadmin/attribute.py
kadmin/command.py
kadm-0.1a1.dist-info/LICENSE
kadm-0.1a1.dist-info/METADATA
kadm-0.1a1.dist-info/WHEEL
kadm-0.1a1.dist-info/entry_points.txt
kadm-0.1a1.dist-info/top_level.txt
kadm-0.1a1.dist-info/zip-safe
kadm-0.1a1.dist-info/RECORD
